ocr_ops/__init__.py
ocr_ops/dependency/__init__.py
ocr_ops/dependency/ffmpeg.py
ocr_ops/framework/__init__.py
ocr_ops/framework/op/__init__.py
ocr_ops/framework/op/abstract_ocr_op.py
ocr_ops/framework/op/drop_op.py
ocr_ops/framework/op/ffmpeg_op.py
ocr_ops/framework/op/ocr_op.py
ocr_ops/framework/op/result/__init__.py
ocr_ops/framework/op/result/ffmeg_result.py
ocr_ops/framework/op/result/ocr_result.py
ocr_ops/framework/pipeline/__init__.py
ocr_ops/framework/pipeline/ocr_pipeline.py
ocr_ops/instances/__init__.py
ocr_ops/instances/cv.py
ocr_ops/instances/ocr.py
ocr_ops/instances/text.py
ocr_ops/run_finding/__init__.py
ocr_ops/run_finding/interval.py
ocr_ops/run_finding/run_finding.py
ocr_ops/test/__init__.py
ocr_ops/test/test_ffmpeg_op.py
ocr_ops/test/test_installs.py
ocr_ops/test/test_ocr_ops.py
ocr_ops/test/test_ocr_pipeline.py
ocr_ops/test/test_run_finding.py
ocr_ops/test/data/blank_card.png
ocr_ops/test/data/joy_of_data.png
ocr_ops/test/data/test.avi
ocr_ops-0.0.0.4.3.2.dist-info/METADATA
ocr_ops-0.0.0.4.3.2.dist-info/WHEEL
ocr_ops-0.0.0.4.3.2.dist-info/licenses/LICENSE
ocr_ops-0.0.0.4.3.2.dist-info/RECORD
